chatpdb/__init__.py
chatpdb/__main__.py
chatpdb/chat/__init__.py
chatpdb/chat/interface.py
chatpdb/chat/llm/__init__.py
chatpdb/chat/llm/interface.py
chatpdb/chat/llm/openai.py
chatpdb/chat/prompts/__init__.py
chatpdb/chat/prompts/ask.py
chatpdb/chat/prompts/explain.py
chatpdb/chat/prompts/system.py
chatpdb/chat/prompts/util.py
chatpdb/debugger/__init__.py
chatpdb/debugger/main.py
chatpdb/frame/__init__.py
chatpdb/frame/main.py
chatpdb/parsing/__init__.py
chatpdb/parsing/interface.py
chatpdb/parsing/vars.py
chatpdb/stdout/__init__.py
chatpdb/stdout/main.py
chatpdb-0.1.14.dist-info/LICENSE
chatpdb-0.1.14.dist-info/METADATA
chatpdb-0.1.14.dist-info/WHEEL
chatpdb-0.1.14.dist-info/top_level.txt
chatpdb-0.1.14.dist-info/RECORD
