Metadata-Version: 2.1
Name: chatpdb
Version: 0.1.14
Summary: A chatgpt enabled python debugger
Author-email: Caelean Barnes <caeleanb@gmail.com>, Evan Doyle <evanmdoyle@gmail.com>
Project-URL: Homepage, https://github.com/never-over/chatpdb
Project-URL: Issues, https://github.com/never-over/chatpdb/issues
Keywords: python,chatgpt,pdb,ai,chat,debugger
Classifier: Programming Language :: Python :: 3
Classifier: License :: OSI Approved :: GNU General Public License v3 (GPLv3)
Classifier: Operating System :: OS Independent
Classifier: Development Status :: 4 - Beta
Classifier: Intended Audience :: Developers
Classifier: Programming Language :: Python
Classifier: Programming Language :: Python :: 3.9
Classifier: Programming Language :: Python :: 3.9
Classifier: Programming Language :: Python :: 3.10
Classifier: Programming Language :: Python :: 3.11
Classifier: Programming Language :: Python :: 3.12
Classifier: Programming Language :: Python :: 3 :: Only
Classifier: Topic :: Software Development :: Libraries :: Python Modules
Requires-Python: >=3.7
License-File: LICENSE
Requires-Dist: ipdb ==0.13.13
Requires-Dist: openai ==1.21.0
Requires-Dist: pydantic ==2.5.3
Requires-Dist: tenacity ==8.2.3
Requires-Dist: rich ==13.7.1
